{
    "all_alone.flac": {
        "A:7": {
            "A#": 1,
            "A#:min": 1
        },
        "A:min7": {
            "C": 6,
            "C:min": 5,
            "E:min": 2,
            "F": 1,
            "G": 4
        },
        "B:7": {
            "C:min": 1,
            "D": 1,
            "E": 2,
            "G#": 1,
            "G#:min": 2
        },
        "B:hdim7": {
            "A:min": 1,
            "D:min": 2,
            "E:min": 1,
            "G": 2
        },
        "Bb:7": {
            "C": 2,
            "D:min": 1,
            "G:min": 2
        },
        "Bb:7/3": {
            "G#": 1
        },
        "C": {
            "C#:min": 1,
            "C:min": 7,
            "D#": 1,
            "E:min": 4,
            "F:min": 2,
            "G": 4
        },
        "C:(3,5,b7,#9,#11,13)": {
            "A:min": 1,
            "C:min": 1
        },
        "C:7": {
            "A:min": 3,
            "C:min": 2,
            "D#": 3,
            "D#:min": 1,
            "F": 3,
            "G:min": 1
        },
        "C:maj6": {
            "A:min": 4,
            "B": 1,
            "E:min": 4
        },
        "C:maj7": {
            "A:min": 1,
            "B": 1,
            "E:min": 3,
            "G": 1,
            "G#:min": 1
        },
        "D:7": {
            "A:min": 3,
            "C": 2,
            "D:min": 2,
            "G": 5,
            "G:min": 2
        },
        "D:min7": {
            "A": 1,
            "A#:min": 1,
            "C": 3,
            "C#:min": 2,
            "C:min": 1,
            "E:min": 1,
            "F": 1,
            "F:min": 2,
            "G": 2
        },
        "E:(3,5,b7,b9)": {
            "A:min": 1,
            "B:min": 1,
            "C": 3,
            "D": 2,
            "D:min": 1,
            "E:min": 3,
            "G": 2
        },
        "E:9": {
            "B:min": 1,
            "D": 1,
            "E:min": 1,
            "G": 2,
            "G#:min": 1
        },
        "E:min7": {
            "A": 1,
            "A:min": 2,
            "B": 1,
            "D": 2,
            "D:min": 2
        },
        "F:(3,5,6,7,9)": {
            "A:min": 3,
            "C:min": 1,
            "F:min": 1
        },
        "F:maj6": {
            "A:min": 4,
            "C": 1,
            "C:min": 1,
            "D": 3,
            "D#": 1,
            "D:min": 4
        },
        "G:7": {
            "C": 8,
            "C:min": 2,
            "D#": 1,
            "D:min": 2,
            "E:min": 3,
            "F:min": 1,
            "G:min": 4
        },
        "G:maj7": {
            "B:min": 2,
            "C": 1,
            "D": 2,
            "E:min": 1,
            "F#:min": 1,
            "G:min": 3
        },
        "G:min7": {
            "C": 1,
            "C:min": 2,
            "D#": 1,
            "F": 2,
            "G": 1
        },
        "N": {
            "A:min": 3,
            "C": 1,
            "C#": 1,
            "D#": 1,
            "D#:min": 1,
            "D:min": 1
        }
    },
    "blue_horizon.flac": {
        "Ab:7": {
            "A#": 1,
            "A#:min": 7,
            "B": 2,
            "C#": 6,
            "C#:min": 3,
            "C:min": 6,
            "D#": 9,
            "D#:min": 20,
            "F": 1,
            "F#": 9,
            "F:min": 8,
            "G#:min": 9
        },
        "Bb:7": {
            "A#:min": 2,
            "C#": 4,
            "C:min": 1,
            "D#": 13,
            "D#:min": 15,
            "D:min": 3,
            "F": 1,
            "F#": 1,
            "F:min": 6,
            "G#": 9,
            "G#:min": 2,
            "G:min": 5,
            "N": 1
        },
        "Eb": {
            "A#": 6,
            "A#:min": 11,
            "B": 1,
            "C#": 3,
            "C:min": 13,
            "D#:min": 26,
            "D:min": 1,
            "F#": 3,
            "F:min": 10,
            "G#": 18,
            "G#:min": 6,
            "G:min": 14
        },
        "Eb:7": {
            "A#": 2,
            "A#:min": 2,
            "C:min": 6,
            "D#:min": 1,
            "F#": 2,
            "F:min": 1,
            "G#": 4,
            "G:min": 3
        },
        "N": {
            "D#": 1,
            "D#:min": 1
        }
    },
    "blues_in_the_closet.flac": {
        "Bb:7": {
            "A": 3,
            "A#:min": 38,
            "C": 21,
            "C#": 12,
            "C#:min": 1,
            "C:min": 30,
            "D#": 112,
            "D#:min": 11,
            "D:min": 17,
            "E": 1,
            "F": 13,
            "F#": 6,
            "F#:min": 1,
            "F:min": 27,
            "G": 2,
            "G#": 2,
            "G#:min": 2,
            "G:min": 122
        },
        "C:min7": {
            "A": 2,
            "A#": 23,
            "A#:min": 3,
            "A:min": 2,
            "C": 3,
            "D#": 17,
            "D:min": 1,
            "E:min": 3,
            "F": 5,
            "F:min": 5,
            "G": 6,
            "G#": 2,
            "G:min": 38
        },
        "D:min7": {
            "A": 1,
            "A#": 21,
            "A#:min": 3,
            "C": 5,
            "C:min": 10,
            "D#": 13,
            "E": 1,
            "F": 1,
            "F:min": 4,
            "G": 5,
            "G#": 1,
            "G#:min": 1,
            "G:min": 32
        },
        "Eb:7": {
            "A#": 81,
            "A#:min": 36,
            "A:min": 2,
            "C": 16,
            "C#": 1,
            "C#:min": 2,
            "C:min": 17,
            "D#:min": 9,
            "D:min": 2,
            "F": 5,
            "F#": 1,
            "F:min": 8,
            "G#": 2,
            "G:min": 41
        },
        "F:7": {
            "A": 1,
            "A#": 68,
            "A#:min": 11,
            "C": 5,
            "C#": 5,
            "C#:min": 2,
            "C:min": 24,
            "D#": 33,
            "D#:min": 2,
            "D:min": 12,
            "E": 1,
            "E:min": 3,
            "F#": 1,
            "F:min": 4,
            "G": 2,
            "G#": 1,
            "G#:min": 3,
            "G:min": 50
        },
        "G:7": {
            "A": 1,
            "A#": 9,
            "A:min": 1,
            "C": 3,
            "C:min": 15,
            "D#": 13,
            "E": 1,
            "E:min": 1,
            "F": 2,
            "G:min": 30
        },
        "N": {
            "A#": 9,
            "A#:min": 5,
            "B": 3,
            "C": 2,
            "C#": 3,
            "C:min": 1,
            "D#": 5,
            "D#:min": 1,
            "D:min": 4,
            "E": 3,
            "E:min": 3,
            "F": 1,
            "F:min": 2,
            "G": 1,
            "G#:min": 4,
            "G:min": 2
        }
    },
    "body_and_soul(hawkins).flac": {
        "A": {
            "C#:min": 1
        },
        "A:7": {
            "C#:min": 1,
            "D": 5,
            "F#:min": 1,
            "G": 1,
            "G:min": 1
        },
        "A:dim": {
            "A#": 1,
            "A#:min": 1,
            "D#:min": 3,
            "F": 2
        },
        "Ab:7": {
            "A": 1,
            "A#": 3,
            "A#:min": 7,
            "C#": 11,
            "D#:min": 4,
            "F#": 4,
            "F#:min": 1,
            "F:min": 3,
            "G#:min": 3,
            "G:min": 1
        },
        "B:7": {
            "E:min": 1,
            "G": 1
        },
        "B:min7/3": {
            "D": 2,
            "G": 1
        },
        "Bb:(3,5,b7,b9)": {
            "A#:min": 1
        },
        "Bb:7": {
            "A#:min": 1,
            "D": 3,
            "D#:min": 3,
            "E": 1,
            "E:min": 2,
            "G": 1,
            "G#:min": 1
        },
        "Bb:min7": {
            "A#": 2,
            "D#": 2,
            "D#:min": 10,
            "D:min": 3,
            "F": 3,
            "F#": 2,
            "F#:min": 2
        },
        "C:7": {
            "E:min": 1,
            "G": 2
        },
        "D": {
            "G:min": 2
        },
        "D:7": {
            "A#": 2,
            "D#:min": 3,
            "F:min": 1
        },
        "D:maj7": {
            "A": 7,
            "C#:min": 1,
            "E": 2,
            "G:min": 1
        },
        "D:min7": {
            "A#": 1,
            "C:min": 3,
            "D": 1,
            "F": 1,
            "G:min": 2
        },
        "Db": {
            "C#:min": 2,
            "D": 4,
            "D#:min": 1,
            "F#": 3,
            "F#:min": 5
        },
        "Db:maj6": {
            "A#:min": 1,
            "A:min": 1,
            "D": 1,
            "D#:min": 3,
            "F": 4,
            "F#:min": 3
        },
        "Db:maj7": {
            "A#": 4,
            "B": 1,
            "C#:min": 1,
            "D": 1,
            "D#:min": 2,
            "F#": 3,
            "F#:min": 1,
            "F:min": 2,
            "G:min": 1
        },
        "E:dim7": {
            "A#:min": 1,
            "A:min": 1,
            "C": 2,
            "C#": 4,
            "C#:min": 4,
            "C:min": 2,
            "F": 1,
            "F:min": 2,
            "G#": 2
        },
        "E:min7": {
            "A": 1,
            "B:min": 1,
            "C#": 1,
            "C#:min": 2,
            "D": 4,
            "D#:min": 1,
            "D:min": 1,
            "F#:min": 1,
            "G": 1
        },
        "Eb:dim": {
            "C": 2,
            "C:min": 1,
            "E:min": 2,
            "G": 2,
            "G:min": 2
        },
        "Eb:min7": {
            "A#": 8,
            "A#:min": 4,
            "A:min": 2,
            "B": 1,
            "C": 3,
            "C#": 1,
            "C#:min": 2,
            "C:min": 3,
            "D#": 6,
            "F#": 3,
            "F#:min": 1,
            "G#": 4,
            "G#:min": 1
        },
        "F#:7": {
            "D": 1,
            "G": 1
        },
        "F:(3,5,b7,b9)": {
            "A#": 1,
            "A#:min": 3,
            "D#": 1,
            "D#:min": 4
        },
        "F:7": {
            "A#": 2,
            "A#:min": 2,
            "D#:min": 1
        },
        "F:7/3": {
            "A#": 1,
            "A#:min": 1,
            "D": 1,
            "D#:min": 1,
            "D:min": 1
        },
        "F:hdim7": {
            "A#:min": 1,
            "C#": 1
        },
        "F:min7": {
            "A#": 1,
            "A#:min": 5,
            "C#": 5,
            "F#": 2,
            "G#": 4,
            "G#:min": 2
        },
        "G:7": {
            "A#": 2,
            "C:min": 1,
            "D": 1,
            "D:min": 3,
            "E:min": 2,
            "G:min": 3
        },
        "G:min7": {
            "D": 1,
            "G": 1
        },
        "Gb:7": {
            "A#": 1,
            "A#:min": 2,
            "F:min": 1
        },
        "Gb:min6": {
            "F#": 1
        },
        "N": {
            "A#": 1,
            "A#:min": 4,
            "B": 2,
            "B:min": 2,
            "D": 3,
            "D#:min": 6,
            "D:min": 1,
            "F#": 4,
            "F#:min": 3
        }
    },
    "cotton_tail.flac": {
        "A:7": {
            "F:min": 1
        },
        "Ab:7": {
            "C#": 1,
            "F:min": 1
        },
        "Bb": {
            "A#:min": 1
        },
        "Bb:maj6": {
            "A#:min": 7,
            "B": 1,
            "C": 11,
            "C#": 6,
            "C:min": 22,
            "D": 2,
            "D#": 6,
            "D#:min": 4,
            "D:min": 2,
            "F": 23,
            "F:min": 23,
            "G:min": 3
        },
        "Bb:maj6/5": {
            "A#:min": 5,
            "B": 2,
            "B:min": 2,
            "C": 1,
            "C:min": 8,
            "D": 2,
            "D#": 4,
            "D#:min": 3,
            "F": 6,
            "F#:min": 1,
            "F:min": 5,
            "G:min": 2
        },
        "C:7": {
            "A#:min": 1,
            "C:min": 4,
            "F": 2,
            "F:min": 5
        },
        "C:min7": {
            "A#": 5,
            "A#:min": 6,
            "C": 8,
            "D#": 1,
            "D:min": 1,
            "F": 17,
            "F#": 1,
            "F:min": 16,
            "G:min": 1
        },
        "D:7": {
            "A:min": 2,
            "B:min": 4,
            "C": 2,
            "D:min": 3,
            "F": 6,
            "F#": 1,
            "F#:min": 1,
            "G": 1
        },
        "D:min7": {
            "A#": 2,
            "A#:min": 1,
            "C": 4,
            "C:min": 5,
            "D#": 1,
            "F": 7,
            "F:min": 3,
            "G:min": 3
        },
        "E:dim7": {
            "A#": 2,
            "A#:min": 3,
            "B": 4,
            "C": 3,
            "C#": 1,
            "C:min": 12,
            "D#": 6,
            "D#:min": 1,
            "F": 4,
            "F:min": 8,
            "G:min": 1
        },
        "Eb:maj6": {
            "A#:min": 1,
            "B": 1,
            "C": 5,
            "C#": 7,
            "C:min": 9,
            "F:min": 9,
            "G:min": 1
        },
        "F#:7": {
            "C:min": 1,
            "F:min": 1
        },
        "F:7": {
            "A#": 10,
            "A#:min": 15,
            "B": 1,
            "C": 12,
            "C#": 4,
            "C:min": 20,
            "D": 3,
            "D#": 3,
            "D#:min": 1,
            "D:min": 2,
            "F:min": 28,
            "G:min": 2
        },
        "F:min": {
            "A#:min": 1
        },
        "G:7": {
            "A#": 2,
            "A:min": 1,
            "B:min": 1,
            "C": 4,
            "C#": 2,
            "C:min": 5,
            "D": 1,
            "D:min": 4,
            "E:min": 1,
            "F": 3,
            "F#": 1,
            "F:min": 3,
            "G:min": 3
        },
        "G:min7": {
            "A#": 7,
            "A#:min": 8,
            "C": 9,
            "C#": 1,
            "C:min": 16,
            "D": 3,
            "D#": 3,
            "D#:min": 2,
            "F": 24,
            "F#": 2,
            "F#:min": 1,
            "F:min": 17
        },
        "N": {
            "A#": 3,
            "A#:min": 2,
            "D#": 1,
            "F:min": 1
        }
    },
    "cotton_tail_fitzgerald.flac": {
        "Bb": {
            "A": 2,
            "A#:min": 13,
            "C#": 1,
            "C:min": 1,
            "D#": 2,
            "F": 1,
            "F#": 1
        },
        "Bb:7": {
            "A#:min": 5,
            "C": 4,
            "C:min": 11,
            "D#": 11,
            "D:min": 3,
            "F": 2,
            "F:min": 2,
            "G:min": 7
        },
        "Bb:maj6": {
            "A#:min": 4,
            "B": 1,
            "C": 1,
            "C:min": 18,
            "D#": 9,
            "D:min": 6,
            "F": 2,
            "F#:min": 2,
            "F:min": 3,
            "G#": 2,
            "G:min": 7
        },
        "Bb:maj6/3": {
            "A": 2,
            "A#:min": 3,
            "C": 2,
            "C#": 1,
            "C#:min": 1,
            "C:min": 5,
            "D": 1,
            "D#": 10,
            "D#:min": 1,
            "D:min": 2,
            "F": 1,
            "F#": 1,
            "G:min": 6
        },
        "Bb:maj6/5": {
            "A": 1,
            "A#:min": 3,
            "C": 3,
            "C#": 1,
            "C:min": 11,
            "D#": 13,
            "G#": 1,
            "G:min": 1
        },
        "C:7": {
            "A": 2,
            "A#": 1,
            "C:min": 15,
            "D#": 7,
            "F": 1,
            "G#": 2,
            "G:min": 6
        },
        "C:min7": {
            "A#": 17,
            "A#:min": 4,
            "B": 1,
            "C": 2,
            "C#": 1,
            "D#": 14,
            "D:min": 5,
            "F": 5,
            "F#": 1,
            "F:min": 3,
            "G:min": 14
        },
        "D:7": {
            "A#": 1,
            "B:min": 1,
            "C:min": 6,
            "D:min": 7,
            "F#:min": 5,
            "G": 2,
            "G:min": 5
        },
        "D:min7": {
            "A#": 2,
            "A#:min": 2,
            "B:min": 1,
            "C": 2,
            "C:min": 14,
            "D#": 6,
            "F": 1,
            "F:min": 1,
            "G#": 1,
            "G:min": 1
        },
        "E:dim7": {
            "A": 2,
            "A#": 3,
            "A#:min": 3,
            "C": 4,
            "C#": 1,
            "C:min": 10,
            "D#": 17,
            "G#": 1,
            "G:min": 3
        },
        "Eb:maj6": {
            "A": 3,
            "A#": 3,
            "A#:min": 1,
            "C": 5,
            "C#:min": 1,
            "C:min": 5,
            "D": 1,
            "D#:min": 1,
            "D:min": 2,
            "G#": 1,
            "G:min": 8
        },
        "F:7": {
            "A": 1,
            "A#": 14,
            "A#:min": 11,
            "B": 1,
            "C": 7,
            "C#": 1,
            "C:min": 52,
            "D": 1,
            "D#": 23,
            "D:min": 10,
            "F#:min": 1,
            "F:min": 4,
            "G": 1,
            "G#": 4,
            "G#:min": 2,
            "G:min": 19
        },
        "G:7": {
            "A#": 7,
            "A#:min": 4,
            "C": 4,
            "C:min": 23,
            "D": 3,
            "D#": 7,
            "D:min": 7,
            "F": 2,
            "F:min": 2,
            "G:min": 6
        },
        "G:min7": {
            "A#": 9,
            "A#:min": 3,
            "B:min": 1,
            "C": 2,
            "C#": 1,
            "C:min": 21,
            "D": 1,
            "D#": 17,
            "D:min": 3,
            "F": 3,
            "F:min": 1,
            "G#": 2
        },
        "N": {
            "A": 1,
            "A#": 3,
            "A#:min": 6,
            "C": 4,
            "C#:min": 1,
            "C:min": 2,
            "D#": 5,
            "E:min": 9
        }
    },
    "girl_from_ipanema.flac": {
        "Ab:7": {
            "A#:min": 4,
            "C#": 3,
            "D#:min": 1,
            "F": 5,
            "F#": 3,
            "F#:min": 2,
            "F:min": 12
        },
        "Bb:7": {
            "A#:min": 1,
            "C#": 3,
            "D#:min": 1,
            "F:min": 2,
            "G:min": 7
        },
        "Bb:9": {
            "A#:min": 2,
            "A:min": 1,
            "C#:min": 4,
            "D#:min": 4,
            "E": 1,
            "F#": 1,
            "F:min": 1
        },
        "Cb:7": {
            "D": 2,
            "D#:min": 1,
            "E": 1,
            "F#:min": 3,
            "F:min": 1,
            "G#": 2,
            "G#:min": 7
        },
        "D:(3,5,6,9)": {
            "B": 2,
            "B:min": 2,
            "E": 1
        },
        "D:7": {
            "A#": 4,
            "B:min": 6,
            "F": 6,
            "F:min": 9,
            "G#": 1,
            "G:min": 1
        },
        "D:7/#11": {
            "A#": 2,
            "B": 2,
            "B:min": 1,
            "C#": 2,
            "C:min": 1,
            "D": 2,
            "D#:min": 1,
            "G#": 4,
            "G#:min": 1,
            "G:min": 3
        },
        "D:maj7": {
            "A": 2,
            "B:min": 3,
            "C#": 2,
            "E:min": 1,
            "F#": 1,
            "F#:min": 5,
            "G": 2
        },
        "D:min7": {
            "A#": 2,
            "A:min": 8,
            "C": 2,
            "D": 1,
            "E:min": 2,
            "G": 1,
            "G:min": 3
        },
        "Db:(3,6,9)/5": {
            "A#": 5,
            "A#:min": 22,
            "B": 1,
            "C:min": 11,
            "D#": 9,
            "D#:min": 1,
            "E": 1,
            "F#:min": 1,
            "F:min": 20,
            "G#": 21,
            "G#:min": 1
        },
        "Db:maj6/5": {
            "A#:min": 3,
            "F": 2,
            "F:min": 8
        },
        "Eb:(3,6,9)/5": {
            "A#:min": 8,
            "C#": 1,
            "C:min": 22,
            "D#:min": 6,
            "F#": 9,
            "F:min": 1,
            "G#": 4
        },
        "Eb:min7": {
            "A#": 3,
            "A#:min": 4,
            "B": 4,
            "F#": 1,
            "G#": 1,
            "G#:min": 2,
            "G:min": 1
        },
        "Eb:min9/5": {
            "A#:min": 7,
            "C#": 6,
            "F#": 16,
            "F:min": 4,
            "G#": 2
        },
        "F:min7": {
            "A#": 2,
            "A#:min": 3,
            "A:min": 1,
            "C#:min": 1,
            "D#:min": 1,
            "G#": 3,
            "G#:min": 1
        },
        "G:7": {
            "A": 1,
            "A#": 1,
            "A:min": 1,
            "B:min": 1,
            "D:min": 4,
            "E:min": 4
        },
        "N": {
            "A#": 2,
            "A#:min": 1,
            "F#": 2,
            "G#": 1,
            "G:min": 3
        }
    },
    "haig_and_haig.flac": {
        "Bb": {
            "A#:min": 22,
            "A:min": 1,
            "C": 4,
            "C#": 1,
            "C:min": 3,
            "D#": 14,
            "D#:min": 1,
            "D:min": 4,
            "F": 5,
            "F#": 2,
            "F:min": 2,
            "G": 1,
            "G:min": 22
        },
        "Bb:7/3": {
            "A": 2,
            "A#:min": 9,
            "C": 1,
            "D#": 10,
            "D#:min": 2,
            "F:min": 1,
            "G:min": 11
        },
        "Bb:7/5": {
            "A#:min": 5,
            "C:min": 3,
            "D#": 6,
            "D:min": 1,
            "F": 3,
            "F:min": 1,
            "G": 3,
            "G:min": 6
        },
        "Bb:min7": {
            "A#": 2,
            "C#": 2,
            "C#:min": 2,
            "D#": 2
        },
        "C:7": {
            "A": 1,
            "A#": 1,
            "A#:min": 1,
            "A:min": 5,
            "D#": 3,
            "E:min": 2,
            "F": 3,
            "G": 4,
            "G:min": 12
        },
        "C:min7": {
            "A": 2,
            "A#": 41,
            "A#:min": 27,
            "C": 3,
            "C#": 2,
            "C#:min": 1,
            "D#": 17,
            "D#:min": 1,
            "D:min": 6,
            "E:min": 2,
            "F": 9,
            "F#": 2,
            "F:min": 1,
            "G": 1,
            "G:min": 18
        },
        "D:7": {
            "A": 3,
            "A#": 7,
            "A#:min": 1,
            "A:min": 5,
            "B:min": 6,
            "D:min": 7,
            "E:min": 2,
            "F": 1,
            "F#": 3,
            "F#:min": 2,
            "G": 7,
            "G:min": 5
        },
        "D:min7": {
            "A#": 11,
            "A#:min": 5,
            "C#": 2,
            "C#:min": 1,
            "C:min": 6,
            "D#": 7,
            "F": 1,
            "F#": 2,
            "G:min": 7
        },
        "E:dim7": {
            "A": 1,
            "A#": 24,
            "A#:min": 4,
            "A:min": 2,
            "C": 1,
            "C:min": 2,
            "D#": 12,
            "F:min": 2,
            "G": 1,
            "G:min": 4
        },
        "Eb:7": {
            "A": 1,
            "A#": 22,
            "A#:min": 3,
            "A:min": 1,
            "C": 1,
            "D#:min": 1,
            "F:min": 2,
            "G:min": 6
        },
        "F:7": {
            "A#": 57,
            "A#:min": 27,
            "A:min": 2,
            "C": 8,
            "C#": 4,
            "C:min": 5,
            "D#": 24,
            "D:min": 8,
            "E:min": 2,
            "F#": 2,
            "F:min": 2,
            "G": 1,
            "G#:min": 1,
            "G:min": 34
        },
        "G:7": {
            "A#": 45,
            "A#:min": 23,
            "A:min": 2,
            "C": 8,
            "C#": 4,
            "C#:min": 3,
            "C:min": 10,
            "D": 1,
            "D#": 18,
            "D#:min": 1,
            "D:min": 18,
            "E:min": 6,
            "F": 7,
            "F#": 3,
            "F:min": 1,
            "G:min": 26
        },
        "N": {
            "A#": 4,
            "D#": 5,
            "D#:min": 1,
            "F": 3,
            "G": 2,
            "G#:min": 4,
            "G:min": 2
        }
    },
    "i_cant_get_started.flac": {
        "A:7": {
            "A#:min": 1,
            "A:min": 4,
            "C": 4,
            "C#": 1,
            "C:min": 2,
            "D": 4,
            "D#": 2,
            "D:min": 4,
            "F": 1,
            "F#:min": 2,
            "G": 1,
            "G#": 1,
            "G:min": 1
        },
        "A:min7": {
            "D:min": 1,
            "E:min": 1
        },
        "Ab:(3,b7,#11)": {
            "A#": 1,
            "B:min": 3,
            "C#": 1,
            "D": 3,
            "F:min": 2,
            "G:min": 1
        },
        "Ab:min7": {
            "B": 1,
            "C#": 2,
            "F#": 1
        },
        "Bb:7": {
            "G#": 1,
            "G:min": 1
        },
        "Bb:min7": {
            "F": 1
        },
        "C#:7": {
            "A#:min": 1
        },
        "C:maj6": {
            "A#:min": 1,
            "A:min": 1,
            "E:min": 1,
            "F:min": 3
        },
        "C:maj7": {
            "A#:min": 1,
            "A:min": 6,
            "C#": 1,
            "C#:min": 1,
            "E": 1,
            "E:min": 2,
            "F": 1,
            "G": 2
        },
        "D:7": {
            "A#": 2,
            "A:min": 1,
            "B:min": 3,
            "C": 1,
            "D:min": 2,
            "G": 2,
            "G:min": 1
        },
        "D:hdim7": {
            "A:min": 1,
            "D": 2,
            "D:min": 2,
            "F:min": 1,
            "G": 3,
            "G#": 1,
            "G:min": 4
        },
        "D:maj6": {
            "A": 1,
            "B:min": 1,
            "G": 1
        },
        "D:maj7": {
            "A": 2,
            "A#:min": 1,
            "B:min": 1,
            "F#": 1,
            "F#:min": 2,
            "G": 1
        },
        "D:min7": {
            "A:min": 4,
            "D": 1,
            "G": 2,
            "G:min": 1
        },
        "Db:7": {
            "A#": 2,
            "A#:min": 3,
            "B:min": 1,
            "C": 2,
            "C#:min": 2,
            "F:min": 1
        },
        "E:7": {
            "A": 1,
            "C": 2,
            "C#:min": 3,
            "D": 1,
            "D#": 1,
            "E:min": 1,
            "G": 3
        },
        "E:hdim7": {
            "C": 4,
            "E:min": 4
        },
        "E:min7": {
            "A": 3,
            "A#:min": 1,
            "A:min": 5,
            "D": 1,
            "D:min": 1,
            "E": 2,
            "F#:min": 1
        },
        "Eb:7": {
            "C": 2,
            "C#:min": 1,
            "C:min": 2,
            "D": 1,
            "G": 2,
            "G:min": 2
        },
        "Eb:maj7": {
            "G:min": 3
        },
        "F:7": {
            "A#": 1,
            "C#": 1,
            "F:min": 1
        },
        "F:maj7": {
            "A": 1,
            "A:min": 1,
            "C#:min": 1
        },
        "F:min7": {
            "C#:min": 1,
            "G#": 1
        },
        "G:(3,5,b7,b9)": {
            "C": 1,
            "C#": 1,
            "E:min": 3,
            "F:min": 1,
            "G:min": 1
        },
        "G:(3,b5,b7,b9)": {
            "C#": 2,
            "F#": 1,
            "G": 1
        },
        "G:7": {
            "A": 1,
            "A#:min": 2,
            "A:min": 1,
            "C": 1,
            "C#": 2,
            "C:min": 1,
            "D": 1,
            "D#": 2,
            "D:min": 3,
            "E:min": 6,
            "F#:min": 1,
            "G:min": 2
        },
        "G:hdim7": {
            "A#:min": 4,
            "C#": 3
        },
        "N": {
            "A:min": 3,
            "C": 2,
            "C#": 3,
            "C#:min": 1,
            "D#": 3,
            "E": 2,
            "E:min": 2,
            "F": 2,
            "F:min": 8,
            "G": 1,
            "G#": 1,
            "G#:min": 1,
            "G:min": 2
        }
    },
    "i_got_rhythm.flac": {
        "Bb": {
            "A#:min": 1,
            "G:min": 2
        },
        "Bb:7": {
            "A#:min": 4,
            "A:min": 2,
            "B": 1,
            "B:min": 1,
            "C#": 3,
            "C#:min": 3,
            "C:min": 3,
            "D": 1,
            "D#": 4,
            "D#:min": 2,
            "D:min": 2,
            "F": 4,
            "F#": 1,
            "F:min": 7,
            "G": 1,
            "G#": 2,
            "G:min": 11
        },
        "Bb:maj6": {
            "A": 2,
            "A#:min": 17,
            "C": 5,
            "C#": 5,
            "C:min": 11,
            "D": 6,
            "D#": 3,
            "D#:min": 5,
            "D:min": 23,
            "E:min": 1,
            "F": 19,
            "F#": 3,
            "F:min": 9,
            "G": 7,
            "G#": 2,
            "G:min": 28
        },
        "Bb:maj6/3": {
            "A#:min": 2,
            "B:min": 1,
            "C#": 3,
            "C:min": 4,
            "D": 1,
            "D#": 5,
            "D#:min": 3,
            "D:min": 1,
            "F": 5,
            "F#": 3,
            "F:min": 5,
            "G#": 2,
            "G:min": 5
        },
        "Bb:maj6/5": {
            "A": 2,
            "A#:min": 8,
            "B": 1,
            "B:min": 1,
            "C#": 3,
            "C:min": 3,
            "D": 1,
            "D#": 3,
            "D#:min": 4,
            "D:min": 10,
            "E:min": 1,
            "F": 2,
            "F:min": 4,
            "G#": 1,
            "G:min": 7
        },
        "C:7": {
            "A:min": 5,
            "C:min": 2,
            "D": 1,
            "D:min": 4,
            "F": 2,
            "F:min": 5,
            "G": 4,
            "G#": 3,
            "G:min": 2
        },
        "C:min7": {
            "A": 6,
            "A#": 29,
            "A#:min": 10,
            "B": 1,
            "B:min": 2,
            "C": 4,
            "D": 2,
            "D#": 3,
            "D#:min": 4,
            "D:min": 14,
            "F": 18,
            "F#": 1,
            "F#:min": 3,
            "F:min": 6,
            "G": 2,
            "G#": 1,
            "G:min": 21
        },
        "D:7": {
            "A": 4,
            "A#": 7,
            "A:min": 3,
            "D#": 1,
            "D:min": 10,
            "G": 2,
            "G:min": 9
        },
        "E:dim7": {
            "A": 2,
            "A#": 16,
            "A#:min": 4,
            "B:min": 2,
            "C": 2,
            "C#": 1,
            "C:min": 4,
            "D": 1,
            "D#": 2,
            "D#:min": 4,
            "D:min": 5,
            "E:min": 1,
            "F": 2,
            "F:min": 5,
            "G": 1,
            "G#": 3,
            "G:min": 6
        },
        "Eb:7": {
            "A#": 19,
            "A#:min": 5,
            "B:min": 1,
            "C#": 5,
            "C:min": 3,
            "D": 4,
            "D#:min": 5,
            "D:min": 5,
            "F": 8,
            "F#": 2,
            "F:min": 3,
            "G": 1,
            "G#": 3,
            "G:min": 7
        },
        "F:7": {
            "A": 4,
            "A#": 54,
            "A#:min": 20,
            "A:min": 2,
            "B": 2,
            "B:min": 1,
            "C": 12,
            "C#": 7,
            "C#:min": 2,
            "C:min": 22,
            "D": 9,
            "D#": 3,
            "D#:min": 6,
            "D:min": 29,
            "E:min": 1,
            "F#": 3,
            "F#:min": 2,
            "F:min": 16,
            "G": 8,
            "G#": 4,
            "G#:min": 1,
            "G:min": 47
        },
        "G:7": {
            "A": 6,
            "A#": 23,
            "A#:min": 12,
            "A:min": 8,
            "B:min": 2,
            "C": 16,
            "C#": 1,
            "C:min": 10,
            "D": 10,
            "D#": 1,
            "D#:min": 4,
            "D:min": 21,
            "E:min": 4,
            "F": 22,
            "F#": 2,
            "F#:min": 5,
            "F:min": 10,
            "G:min": 19
        },
        "N": {
            "A#": 3,
            "A#:min": 2,
            "D#": 5,
            "D#:min": 6,
            "D:min": 1,
            "E": 3,
            "E:min": 3,
            "F": 2,
            "F#": 1,
            "G": 2,
            "G:min": 7
        }
    },
    "in_a_mellotone.flac": {
        "A:dim": {
            "C:min": 2,
            "D#": 2
        },
        "Ab": {
            "C#": 3,
            "C#:min": 1,
            "C:min": 7,
            "D#": 1,
            "F:min": 6,
            "G#:min": 3
        },
        "Ab:7": {
            "A#:min": 2,
            "C#": 4,
            "C:min": 1,
            "D#": 1,
            "D#:min": 3,
            "F": 1,
            "F:min": 14,
            "G#:min": 1
        },
        "Ab:9": {
            "D#": 2,
            "F:min": 1,
            "G": 1,
            "G#:min": 8
        },
        "Ab:dim": {
            "C:min": 3,
            "D#": 1,
            "G": 1
        },
        "Ab:maj6": {
            "F": 1,
            "F:min": 3,
            "G#:min": 1
        },
        "Ab:maj7": {
            "C#": 1,
            "C:min": 5,
            "F:min": 5
        },
        "Bb:7": {
            "A#:min": 3,
            "C": 1,
            "C#": 3,
            "C:min": 5,
            "D#": 3,
            "D:min": 2,
            "F": 5,
            "F:min": 19,
            "G#": 2,
            "G:min": 1
        },
        "D:dim": {
            "A#": 1,
            "C#": 2,
            "D:min": 1,
            "F:min": 5,
            "G": 1,
            "G#:min": 1
        },
        "Db:7": {
            "F:min": 3
        },
        "Db:maj7": {
            "A#:min": 15,
            "C#:min": 1,
            "F#": 3,
            "F:min": 16,
            "G#": 4
        },
        "Db:min7": {
            "C#": 3,
            "F:min": 1,
            "G#": 3,
            "G#:min": 3
        },
        "Eb": {
            "C:min": 2,
            "F:min": 2
        },
        "Eb:7": {
            "A#": 1,
            "A#:min": 2,
            "B": 1,
            "C#": 2,
            "C:min": 10,
            "F:min": 8,
            "G": 3,
            "G#": 4,
            "G#:min": 1
        },
        "Eb:maj6": {
            "C:min": 6,
            "F:min": 1,
            "G#": 1
        },
        "Eb:min7": {
            "C#": 2,
            "C#:min": 1,
            "F#": 2,
            "F:min": 2,
            "G#": 4,
            "G#:min": 1
        },
        "F#:7": {
            "C#": 2,
            "D#:min": 1,
            "D:min": 1,
            "F:min": 1
        },
        "F#:9": {
            "B": 1,
            "D:min": 1,
            "F": 1
        },
        "F#:dim": {
            "C:min": 2
        },
        "F:7": {
            "A#": 2,
            "A#:min": 1,
            "C#": 1,
            "C:min": 3,
            "D:min": 4,
            "F:min": 9,
            "G#": 3,
            "G#:min": 1
        },
        "F:9": {
            "C:min": 2,
            "F:min": 2
        },
        "G:7": {
            "C#": 1,
            "D#:min": 1,
            "F:min": 1,
            "G#:min": 1
        },
        "G:9": {
            "B": 1,
            "G#:min": 4
        },
        "G:dim": {
            "C:min": 2
        },
        "N": {
            "A#:min": 2,
            "C#": 2,
            "C:min": 1,
            "D#": 1,
            "F:min": 3,
            "G#": 2,
            "G:min": 1
        }
    },
    "isfahan.flac": {
        "A:hdim7": {
            "A:min": 1,
            "D:min": 1,
            "F": 2
        },
        "A:maj7": {
            "C#": 2,
            "C#:min": 2
        },
        "A:maj9": {
            "C#": 1,
            "C#:min": 1,
            "E": 1,
            "F#:min": 1,
            "G#:min": 1
        },
        "Ab:(3,#5,b7)": {
            "A": 7,
            "A:min": 3,
            "C#": 2,
            "C#:min": 5,
            "D#:min": 1,
            "D:min": 5,
            "F": 3,
            "F#:min": 2,
            "G#": 1
        },
        "Ab:(3,5,b7,b9)": {
            "C#": 2,
            "D:min": 1
        },
        "Ab:(3,5,b7,b9,13)": {
            "A": 2,
            "A#:min": 1,
            "A:min": 1,
            "C#": 2,
            "C#:min": 2,
            "D#:min": 1,
            "D:min": 2,
            "F#": 1
        },
        "Ab:7": {
            "C#": 3,
            "F#": 1,
            "F#:min": 1,
            "F:min": 2
        },
        "B:min/7": {
            "C:min": 1,
            "E": 1,
            "G": 1,
            "G#:min": 1
        },
        "Bb:(3,#5,b7)": {
            "A#": 2,
            "A#:min": 1,
            "C#": 2,
            "C#:min": 1,
            "D": 1,
            "D#:min": 4,
            "D:min": 1,
            "F#": 2,
            "G#:min": 1,
            "G:min": 3
        },
        "Bb:7": {
            "C#": 1,
            "D:min": 1,
            "F:min": 1,
            "G#:min": 1
        },
        "Bb:maj7": {
            "C#": 3,
            "D:min": 4,
            "E": 1,
            "F#:min": 3,
            "G#:min": 1
        },
        "C:(3,#5,b7,b9)": {
            "A:min": 2,
            "C#:min": 1,
            "F": 1,
            "F:min": 2
        },
        "C:(3,5,b7,b9)": {
            "A#:min": 2,
            "A:min": 2,
            "C#": 1,
            "C#:min": 1,
            "D#": 1,
            "G#": 1
        },
        "C:(3,5,b7,b9,b13)": {
            "A:min": 1,
            "C#:min": 2,
            "E": 1,
            "G#": 1
        },
        "D:(3,5,b7,b9)": {
            "D:min": 1,
            "G:min": 1
        },
        "D:7": {
            "C#": 1,
            "G:min": 1
        },
        "Db:(3,5,7,#11)": {
            "B:min": 1,
            "C": 1,
            "C:min": 1,
            "E:min": 1,
            "G": 3
        },
        "Db:maj6": {
            "D#": 1,
            "D#:min": 1,
            "F:min": 1,
            "G#": 2
        },
        "Db:maj7": {
            "A#:min": 2,
            "F": 1,
            "F#:min": 2,
            "F:min": 6,
            "G#": 1
        },
        "Db:maj9": {
            "A#:min": 1,
            "D#": 2,
            "D#:min": 3,
            "F#": 1,
            "F:min": 1,
            "G#": 2
        },
        "E:maj7": {
            "C": 1,
            "G#:min": 1
        },
        "Eb:(3,5,b7,9,13)": {
            "A:min": 1,
            "C#:min": 2,
            "C:min": 4,
            "E": 1,
            "G#": 1,
            "G#:min": 1,
            "G:min": 1
        },
        "Eb:9": {
            "A#": 5,
            "A#:min": 7,
            "C#": 8,
            "D#:min": 3,
            "F:min": 6,
            "G#": 4,
            "G#:min": 6
        },
        "Eb:maj7": {
            "G#:min": 1,
            "G:min": 1
        },
        "F:(3,5,b7,#11)": {
            "A:min": 1,
            "D:min": 1,
            "E": 1,
            "F:min": 4
        },
        "F:maj7": {
            "C": 1
        },
        "F:min6": {
            "C#": 1,
            "F": 1
        },
        "G/b5": {
            "B:min": 1,
            "C": 1,
            "C#": 1,
            "C#:min": 1,
            "E:min": 1,
            "F#:min": 2,
            "G": 2
        },
        "G:hdim7": {
            "A#:min": 2,
            "D#": 1,
            "F:min": 1,
            "G:min": 1
        },
        "G:min6": {
            "C": 2,
            "D#": 1
        },
        "Gb:maj6": {
            "D#:min": 1,
            "F#:min": 1,
            "G#": 1
        },
        "Gb:maj7": {
            "C#": 1,
            "D#:min": 1,
            "G#": 1,
            "G#:min": 2
        },
        "N": {
            "A#": 1,
            "A#:min": 7,
            "C#": 5,
            "C#:min": 3,
            "D#": 3,
            "D#:min": 1,
            "E:min": 1,
            "F:min": 5,
            "G#": 7,
            "G#:min": 5
        }
    },
    "king_porter_stomp.flac": {
        "Ab": {
            "A#": 1,
            "C#": 1,
            "C:min": 3,
            "D#": 13,
            "D#:min": 4,
            "F#": 1,
            "F:min": 5,
            "G#:min": 4
        },
        "Ab/5": {
            "A#": 2,
            "A#:min": 1,
            "C#": 1,
            "D#": 1
        },
        "Ab:7": {
            "A#:min": 3,
            "C#": 4,
            "D#": 4,
            "D#:min": 2,
            "F#": 2
        },
        "Ab:maj6": {
            "A#": 3,
            "D#": 1,
            "F": 1,
            "F:min": 1
        },
        "B:dim": {
            "F:min": 1,
            "G#": 1
        },
        "Bb:7": {
            "A#:min": 7,
            "C#": 1,
            "D#": 9,
            "F#": 1,
            "F:min": 1,
            "G#": 1,
            "G:min": 2
        },
        "Bb:min": {
            "A#": 2,
            "D#": 3,
            "D#:min": 1,
            "F:min": 2,
            "G#": 1
        },
        "C:7": {
            "D#": 2,
            "F": 1,
            "F:min": 3,
            "G#": 1,
            "G:min": 1
        },
        "D:dim7": {
            "A#:min": 2,
            "C#": 3,
            "D#": 1,
            "G#": 2
        },
        "Db": {
            "A#:min": 7,
            "C#:min": 3,
            "D#": 3,
            "D#:min": 1,
            "F#": 5,
            "G#:min": 1
        },
        "Db/3": {
            "C#:min": 4,
            "F#": 1
        },
        "Db/5": {
            "A#:min": 2,
            "D#": 3,
            "D#:min": 2,
            "F#": 1,
            "G#": 1
        },
        "Db:7/5": {
            "A#:min": 3,
            "C#:min": 3,
            "D#": 2,
            "D#:min": 1,
            "F#": 10
        },
        "Db:maj6": {
            "D#:min": 2,
            "F#": 2,
            "F:min": 1
        },
        "Eb:7": {
            "A#:min": 9,
            "C": 1,
            "C#": 1,
            "C:min": 2,
            "D#:min": 4,
            "F#": 1,
            "F:min": 2,
            "G#": 6,
            "G:min": 2
        },
        "F:7": {
            "A#": 3,
            "A#:min": 7,
            "C#": 1,
            "C:min": 1,
            "D#": 7,
            "F:min": 4,
            "G#": 2
        },
        "F:min": {
            "C": 4,
            "C#": 1,
            "G#": 1
        },
        "G:dim7": {
            "A#:min": 5,
            "C#": 6,
            "C#:min": 3,
            "D#": 6,
            "D#:min": 3,
            "F#": 16
        },
        "G:min": {
            "C#": 3,
            "F#": 2
        },
        "Gb": {
            "A#:min": 3,
            "C#": 6,
            "C#:min": 7,
            "D#": 3,
            "D#:min": 5
        },
        "Gb:7": {
            "A#:min": 1,
            "C#": 2,
            "D#:min": 1,
            "F:min": 3,
            "G#": 3
        },
        "Gb:maj6": {
            "C#": 1,
            "C#:min": 1
        },
        "N": {
            "A#:min": 2,
            "C#": 2,
            "D#": 1,
            "F:min": 1,
            "G#": 1
        }
    },
    "lester_leaps_in.flac": {
        "Bb": {
            "D#": 1,
            "D#:min": 1
        },
        "Bb:maj6": {
            "A": 1,
            "A#:min": 6,
            "C": 4,
            "C:min": 2,
            "D": 1,
            "D#": 14,
            "D#:min": 1,
            "D:min": 1,
            "F": 5,
            "F:min": 1,
            "G:min": 23
        },
        "Bb:maj6/5": {
            "A": 2,
            "A#:min": 2,
            "A:min": 2,
            "C": 1,
            "C:min": 1,
            "D#": 5,
            "F": 1,
            "F:min": 1,
            "G:min": 7
        },
        "C:7": {
            "A#": 4,
            "A:min": 1,
            "C:min": 1,
            "D#": 1,
            "E:min": 4,
            "F": 3,
            "F:min": 1,
            "G:min": 4
        },
        "C:min7": {
            "A": 1,
            "A#": 18,
            "A#:min": 6,
            "C": 7,
            "C#": 2,
            "D#": 9,
            "F": 1,
            "F#": 1,
            "F:min": 1,
            "G:min": 13
        },
        "D:7": {
            "A": 1,
            "A#": 1,
            "A:min": 5,
            "B:min": 1,
            "C": 6,
            "D:min": 1,
            "E:min": 2,
            "F": 4,
            "F:min": 2,
            "G:min": 3
        },
        "D:min7": {
            "A#": 8,
            "A#:min": 4,
            "C": 3,
            "C#:min": 1,
            "E:min": 1,
            "F#": 1,
            "G:min": 2
        },
        "E:dim7": {
            "A#": 3,
            "A#:min": 1,
            "A:min": 1,
            "C": 1,
            "C:min": 3,
            "D#": 6,
            "E": 1,
            "F": 2,
            "G:min": 8
        },
        "Eb:maj6": {
            "A#": 5,
            "A#:min": 3,
            "C": 2,
            "C#": 1,
            "C:min": 1,
            "E": 1,
            "F": 1,
            "G:min": 8
        },
        "F:7": {
            "A": 1,
            "A#": 23,
            "A#:min": 8,
            "C": 13,
            "C#": 2,
            "C#:min": 1,
            "C:min": 8,
            "D#": 16,
            "D:min": 3,
            "E:min": 2,
            "F#": 1,
            "F:min": 2,
            "G#": 3,
            "G:min": 25
        },
        "G:7": {
            "A#": 1,
            "A#:min": 1,
            "A:min": 1,
            "C": 5,
            "D:min": 2,
            "E:min": 10,
            "F": 5,
            "F:min": 1,
            "G:min": 2
        },
        "G:min7": {
            "A": 2,
            "A#": 27,
            "A#:min": 9,
            "A:min": 1,
            "C": 7,
            "C#:min": 1,
            "C:min": 2,
            "D#": 7,
            "D#:min": 1,
            "D:min": 1,
            "F": 3,
            "F#": 1,
            "F:min": 2
        },
        "N": {
            "A": 1,
            "A#": 22,
            "A#:min": 12,
            "D#": 4,
            "D#:min": 4,
            "F#": 1,
            "G:min": 1
        }
    },
    "misterioso.flac": {
        "Bb:7": {
            "A": 2,
            "A#:min": 19,
            "A:min": 3,
            "C": 6,
            "C#": 9,
            "C#:min": 3,
            "C:min": 19,
            "D#": 31,
            "D#:min": 2,
            "D:min": 11,
            "E": 1,
            "E:min": 1,
            "F": 4,
            "F#": 6,
            "F#:min": 1,
            "F:min": 18,
            "G": 3,
            "G#": 5,
            "G#:min": 7,
            "G:min": 20
        },
        "C:min7": {
            "A": 1,
            "A#": 1,
            "C": 5,
            "C#": 2,
            "C#:min": 4,
            "D": 1,
            "D#": 2,
            "D:min": 1,
            "F": 1,
            "G#": 3
        },
        "Eb:7": {
            "A#": 4,
            "A#:min": 16,
            "A:min": 1,
            "C": 1,
            "C#": 5,
            "C:min": 1,
            "D#:min": 4,
            "D:min": 2,
            "E": 1,
            "F": 1,
            "F#": 4,
            "F:min": 8,
            "G#": 4,
            "G:min": 5
        },
        "F:7": {
            "A": 3,
            "A#": 3,
            "A#:min": 3,
            "C": 2,
            "C#": 1,
            "C#:min": 5,
            "C:min": 6,
            "D#": 5,
            "D:min": 3,
            "F#": 1,
            "F:min": 2,
            "G#": 4,
            "G#:min": 1,
            "G:min": 1
        },
        "N": {
            "A#": 2,
            "A#:min": 2,
            "C#": 1,
            "C:min": 2,
            "D#": 5,
            "D:min": 2,
            "F": 2,
            "F:min": 1,
            "G#": 4,
            "G#:min": 4,
            "G:min": 5
        }
    },
    "oh_lady_be_good.flac": {
        "A:7": {
            "B": 1,
            "B:min": 1,
            "C": 1,
            "C:min": 1,
            "D": 1,
            "E:min": 2
        },
        "A:min7": {
            "A": 1,
            "A#": 1,
            "C": 22,
            "C#:min": 1,
            "C:min": 17,
            "D": 3,
            "D#": 1,
            "D:min": 4,
            "E:min": 8,
            "F": 1,
            "G": 8,
            "G#": 2,
            "G:min": 5
        },
        "B:(3,5,b7,b9)": {
            "C#:min": 1,
            "E": 4,
            "E:min": 1,
            "G": 5,
            "G:min": 2
        },
        "B:min7": {
            "C:min": 3,
            "D": 1,
            "D:min": 1,
            "E:min": 1,
            "F": 2,
            "G": 9,
            "G#:min": 1,
            "G:min": 1
        },
        "Bb:7": {
            "B:min": 1,
            "C": 5,
            "C:min": 3,
            "E:min": 2,
            "F": 1,
            "G": 5,
            "G:min": 7
        },
        "C": {
            "A#:min": 1,
            "C:min": 1,
            "D#": 1,
            "F": 1,
            "G": 2,
            "G:min": 1
        },
        "C#:dim7": {
            "A#:min": 1,
            "A:min": 1,
            "C": 1,
            "C:min": 4,
            "D": 1,
            "D#": 1,
            "D:min": 1,
            "G": 3,
            "G:min": 5
        },
        "C:7": {
            "A:min": 2,
            "C:min": 9,
            "D": 3,
            "D#": 1,
            "D#:min": 1,
            "D:min": 1,
            "E:min": 2,
            "G": 13,
            "G:min": 9
        },
        "C:dim7": {
            "C:min": 1,
            "G:min": 1
        },
        "D:7": {
            "A:min": 1,
            "B": 1,
            "B:min": 1,
            "C": 9,
            "C:min": 14,
            "D#": 2,
            "D:min": 3,
            "E:min": 1,
            "F:min": 1,
            "G": 24,
            "G:min": 9
        },
        "D:hdim7": {
            "C:min": 1,
            "G": 1
        },
        "D:min7": {
            "C": 1,
            "C:min": 2,
            "D": 1,
            "G": 1,
            "G:min": 3
        },
        "E:min7": {
            "A": 1,
            "B": 2,
            "C": 6,
            "C#:min": 1,
            "C:min": 6,
            "D": 2,
            "D#": 4,
            "G": 9,
            "G:min": 4
        },
        "F#:hdim7": {
            "C": 1,
            "E": 2,
            "G": 3
        },
        "G:7": {
            "C": 2,
            "D:min": 1,
            "G:min": 2
        },
        "G:hdim7": {
            "G": 1,
            "G:min": 1
        },
        "G:maj6": {
            "A#": 1,
            "C": 2,
            "C:min": 6,
            "D": 1,
            "D#": 1,
            "G:min": 2
        },
        "G:maj7": {
            "A:min": 1,
            "C": 13,
            "C:min": 13,
            "D": 4,
            "E:min": 1,
            "F:min": 1,
            "G#:min": 1,
            "G:min": 12
        },
        "N": {
            "A#": 6,
            "B": 1,
            "B:min": 4,
            "C": 3,
            "C:min": 5,
            "D": 4,
            "D#": 3,
            "D#:min": 1,
            "D:min": 5,
            "F#": 4,
            "F#:min": 5,
            "G": 9,
            "G:min": 9
        }
    },
    "one_by_one.flac": {
        "A:(3,#5,b7,#9)": {
            "C": 1,
            "C:min": 1,
            "D": 1,
            "D:min": 5,
            "E": 1,
            "E:min": 1,
            "F": 1,
            "G": 7,
            "G:min": 5
        },
        "A:hdim7": {
            "A#": 3,
            "A:min": 11,
            "B:min": 1,
            "C": 9,
            "C:min": 17,
            "D": 2,
            "D#": 2,
            "D#:min": 1,
            "D:min": 8,
            "F": 12,
            "F#:min": 3,
            "F:min": 3,
            "G": 6,
            "G#": 1,
            "G:min": 20
        },
        "Ab:7": {
            "A#": 4,
            "A:min": 4,
            "C": 7,
            "C:min": 19,
            "D": 2,
            "D#": 3,
            "D:min": 2,
            "F": 4,
            "F#": 1,
            "F#:min": 3,
            "G": 2,
            "G:min": 23
        },
        "B:hdim7": {
            "D": 1,
            "D:min": 1,
            "G": 6
        },
        "Bb:7/5": {
            "A#:min": 2,
            "B:min": 2,
            "C": 9,
            "C#": 1,
            "C:min": 7,
            "D#": 7,
            "D:min": 2,
            "F": 3,
            "F:min": 7,
            "G": 6,
            "G:min": 27
        },
        "Bb:maj7": {
            "A:min": 1,
            "C": 8,
            "C:min": 19,
            "D#": 10,
            "D#:min": 1,
            "D:min": 6,
            "F": 11,
            "F:min": 1,
            "G": 4,
            "G:min": 15
        },
        "C:min7": {
            "A#": 7,
            "B": 1,
            "B:min": 2,
            "C": 4,
            "D#": 4,
            "D:min": 4,
            "F": 9,
            "G": 5,
            "G:min": 6
        },
        "D:(3,#5,b7,#9)": {
            "A#": 7,
            "B:min": 1,
            "C": 11,
            "C#": 1,
            "C:min": 24,
            "D": 5,
            "D:min": 5,
            "E:min": 1,
            "F": 6,
            "F:min": 1,
            "G": 18,
            "G:min": 48
        },
        "D:min7": {
            "A#": 1,
            "C": 3,
            "C:min": 1,
            "D": 1,
            "F": 2,
            "F#:min": 1,
            "G": 11,
            "G:min": 10
        },
        "E:(3,5,b7,#9)": {
            "A#": 1,
            "C": 1,
            "D:min": 1,
            "E:min": 1,
            "G": 5,
            "G:min": 3
        },
        "E:hdim7": {
            "A#": 8,
            "A#:min": 2,
            "B:min": 2,
            "C": 7,
            "C#": 2,
            "C:min": 3,
            "D": 2,
            "D#": 2,
            "D:min": 1,
            "E": 1,
            "E:min": 2,
            "F": 4,
            "F:min": 5,
            "G": 9,
            "G:min": 22
        },
        "Eb:maj7": {
            "A#": 7,
            "D:min": 5,
            "F": 1
        },
        "F:7": {
            "A#": 7,
            "C": 1,
            "C:min": 8,
            "D:min": 6,
            "G": 4,
            "G:min": 7
        },
        "F:min": {
            "A#": 6,
            "G:min": 1
        },
        "G:(b3,5,b7,11)": {
            "A#": 10,
            "C": 3,
            "C:min": 7,
            "D:min": 8,
            "F": 1,
            "G": 9
        },
        "G:min7": {
            "A#": 14,
            "A#:min": 1,
            "B:min": 1,
            "C": 10,
            "C#": 1,
            "C:min": 23,
            "D": 1,
            "D#": 4,
            "D:min": 1,
            "E:min": 1,
            "F": 2,
            "F:min": 2,
            "G": 18,
            "G#": 1
        },
        "N": {
            "A#": 1,
            "A#:min": 11,
            "B": 2,
            "D#": 2,
            "E": 4,
            "E:min": 5,
            "F": 7,
            "F:min": 1,
            "G#:min": 3
        }
    },
    "organ_grinders_swing.flac": {
        "Ab:maj6": {
            "C:min": 1,
            "D#": 1,
            "F": 1,
            "F:min": 2
        },
        "Bb:7": {
            "A#:min": 2,
            "B": 1,
            "C": 1,
            "C:min": 1,
            "D#": 1,
            "D#:min": 1,
            "F": 2,
            "F#:min": 1,
            "F:min": 1,
            "G": 4,
            "G#": 2,
            "G:min": 6
        },
        "C:maj6": {
            "A:min": 2,
            "C:min": 5,
            "D": 1,
            "D:min": 1,
            "E:min": 1,
            "F": 3,
            "G": 3,
            "G:min": 6
        },
        "D:7": {
            "A": 1,
            "A:min": 12,
            "B:min": 2,
            "C": 5,
            "D:min": 1,
            "E:min": 4,
            "F": 8,
            "F#": 1,
            "G": 4,
            "G:min": 2
        },
        "Eb": {
            "A#": 8,
            "C:min": 17,
            "D#:min": 4,
            "F": 3,
            "F:min": 8,
            "G": 5,
            "G#": 5,
            "G:min": 4
        },
        "G": {
            "A": 3,
            "A#:min": 2,
            "A:min": 3,
            "B:min": 5,
            "C": 8,
            "C#": 2,
            "C#:min": 1,
            "C:min": 3,
            "D#": 2,
            "D:min": 4,
            "E:min": 7,
            "F": 1,
            "F#": 4,
            "F#:min": 3,
            "G:min": 5
        },
        "N": {
            "A#": 1,
            "A#:min": 3,
            "A:min": 1,
            "B:min": 2,
            "C": 3,
            "C#": 1,
            "C:min": 1,
            "D": 2,
            "D#": 2,
            "D#:min": 2,
            "E": 1,
            "E:min": 4,
            "F": 2,
            "F#": 1,
            "F#:min": 1,
            "F:min": 2,
            "G": 2,
            "G:min": 2
        }
    },
    "rockin_chair.flac": {
        "A:hdim7": {
            "C:min": 1,
            "D": 1,
            "D#": 1,
            "D:min": 1,
            "F": 2
        },
        "Ab": {
            "A#:min": 1,
            "C#": 1,
            "D#": 1,
            "F:min": 2,
            "G#:min": 3
        },
        "Ab:7": {
            "A#:min": 3,
            "D#": 2,
            "D#:min": 2,
            "F:min": 1
        },
        "Bb:7": {
            "A#:min": 1,
            "C#": 5,
            "C:min": 2,
            "D#": 4,
            "D#:min": 1,
            "F:min": 6,
            "G#": 2,
            "G#:min": 1
        },
        "C#:7": {
            "A#:min": 2,
            "F#:min": 1,
            "F:min": 1,
            "G#:min": 1
        },
        "C:7": {
            "D#": 2,
            "E": 1,
            "F": 1,
            "F:min": 1,
            "G#": 1,
            "G:min": 1
        },
        "D:(3,5,b7,b9)": {
            "C": 2,
            "F": 2
        },
        "D:7": {
            "D:min": 1,
            "G:min": 1
        },
        "Eb": {
            "A#:min": 1,
            "C:min": 1,
            "E:min": 1
        },
        "Eb:7": {
            "A#:min": 4,
            "F#": 1,
            "F:min": 1
        },
        "Eb:maj6": {
            "A#": 3,
            "A#:min": 1,
            "C:min": 2,
            "D#:min": 1,
            "E": 1,
            "F": 2,
            "F#": 1,
            "G#": 1,
            "G#:min": 2,
            "G:min": 1
        },
        "F#:dim7": {
            "C:min": 1,
            "D#": 1
        },
        "F#:min6": {
            "B": 1,
            "B:min": 1,
            "C#": 1
        },
        "F:7": {
            "C": 2,
            "C:min": 5,
            "D#": 1,
            "D:min": 1,
            "F:min": 1
        },
        "F:hdim7": {
            "A#": 1,
            "C#": 3,
            "D#": 1,
            "E": 1,
            "G#:min": 5
        },
        "F:min6": {
            "A#": 1,
            "C#": 1,
            "D#": 1,
            "G#": 1
        },
        "F:min7": {
            "C#": 1,
            "C:min": 1,
            "D#": 2,
            "D#:min": 1
        },
        "G:min": {
            "C": 5,
            "C:min": 1
        },
        "N": {
            "A#": 22,
            "A#:min": 16,
            "B": 1,
            "C#": 3,
            "D#": 5,
            "D#:min": 1,
            "E:min": 1,
            "F:min": 4
        }
    },
    "summertime.flac": {
        "Bb:min": {
            "C#": 1,
            "C:min": 1,
            "D#": 9,
            "D#:min": 2,
            "F": 13,
            "F#": 3,
            "F#:min": 1,
            "F:min": 28,
            "G#": 7,
            "G#:min": 1
        },
        "C:7": {
            "A": 1,
            "A#:min": 3,
            "A:min": 1,
            "C#:min": 1,
            "D#:min": 1,
            "F#": 5
        },
        "C:min6": {
            "A#:min": 2,
            "C#": 4,
            "D#": 1,
            "F:min": 1,
            "G#": 6
        },
        "Db:maj6": {
            "A#:min": 1,
            "C:min": 2,
            "F": 1,
            "F:min": 4,
            "G#": 5
        },
        "Eb:(3,5,#11,13)": {
            "A#:min": 3,
            "C:min": 3,
            "F": 2,
            "F:min": 5
        },
        "Eb:min": {
            "A#": 2,
            "A#:min": 7,
            "C#": 6,
            "C:min": 1,
            "D#": 1,
            "D:min": 1,
            "F": 10,
            "F#": 7,
            "F#:min": 2,
            "F:min": 7,
            "G#": 10,
            "G#:min": 2
        },
        "F:7": {
            "A#": 1,
            "A#:min": 31,
            "A:min": 1,
            "C": 1,
            "C#": 8,
            "C#:min": 1,
            "C:min": 3,
            "D#": 11,
            "D#:min": 2,
            "F#": 4,
            "F#:min": 3,
            "F:min": 38,
            "G#": 17
        },
        "N": {
            "A#:min": 1,
            "F": 2
        }
    },
    "the_man_i_love.flac": {
        "Bb:7": {
            "A#:min": 2,
            "B:min": 1,
            "C:min": 18,
            "D#": 15,
            "D:min": 2,
            "E": 1,
            "E:min": 1,
            "F": 1,
            "F:min": 17,
            "G": 8,
            "G#": 12,
            "G#:min": 5,
            "G:min": 12
        },
        "Bb:min7": {
            "A#": 2,
            "C": 5,
            "C#": 11,
            "D#": 1,
            "D#:min": 4,
            "E:min": 2,
            "F": 4,
            "F:min": 19,
            "G:min": 1
        },
        "C:7": {
            "A#": 2,
            "A#:min": 4,
            "A:min": 6,
            "C:min": 21,
            "D#": 10,
            "E": 1,
            "E:min": 3,
            "F": 6,
            "F:min": 13,
            "G": 1,
            "G#": 5,
            "G:min": 2
        },
        "C:min": {
            "C": 5,
            "D#": 1,
            "F": 2,
            "F:min": 3,
            "G": 4,
            "G#": 4,
            "G:min": 1
        },
        "C:min6": {
            "C": 1,
            "F:min": 1
        },
        "D:min7": {
            "A:min": 2,
            "C": 3,
            "C:min": 5,
            "D#": 3,
            "F": 5,
            "F:min": 1,
            "G": 2,
            "G#": 2,
            "G#:min": 2,
            "G:min": 1
        },
        "Eb:maj6": {
            "A#": 3,
            "A#:min": 4,
            "C": 8,
            "C:min": 28,
            "D": 1,
            "D#:min": 4,
            "D:min": 1,
            "E:min": 1,
            "F": 1,
            "F#": 1,
            "F:min": 13,
            "G": 2,
            "G#": 12,
            "G#:min": 3,
            "G:min": 9
        },
        "Eb:min7": {
            "A#": 2,
            "A#:min": 8,
            "C#": 2,
            "C:min": 1,
            "D#": 10,
            "F#": 2,
            "F:min": 4,
            "G#": 2
        },
        "F:7": {
            "A#": 2,
            "D#": 2,
            "F:min": 1,
            "G:min": 2
        },
        "F:hdim7": {
            "C": 4,
            "C:min": 7,
            "D#": 4,
            "E": 3,
            "E:min": 3,
            "F:min": 2,
            "G": 5,
            "G#": 7,
            "G#:min": 12
        },
        "F:min7": {
            "C": 3,
            "C:min": 3,
            "F": 1,
            "G": 1,
            "G#": 1
        },
        "G:7": {
            "A#": 2,
            "C": 3,
            "C:min": 17,
            "D#": 7,
            "D:min": 4,
            "E:min": 1,
            "F": 3,
            "F:min": 7,
            "G#": 2,
            "G#:min": 4,
            "G:min": 5
        },
        "G:min7": {
            "C": 5,
            "C:min": 1,
            "E:min": 2,
            "F:min": 1
        },
        "N": {
            "B": 1,
            "C": 12,
            "C:min": 5,
            "D#": 3,
            "E": 1,
            "E:min": 7,
            "F#": 1,
            "F:min": 2,
            "G": 3
        }
    },
    "watermelon_man.flac": {
        "A:7": {
            "C#": 1,
            "D#:min": 1
        },
        "Ab:(4,5,b7,13)": {
            "C#": 2,
            "D#": 2,
            "D#:min": 2,
            "G#": 4,
            "G#:min": 2
        },
        "Ab:7": {
            "C#": 18,
            "D#": 2,
            "D#:min": 10,
            "F:min": 3,
            "G#:min": 14
        },
        "Ab:min6": {
            "G#": 2
        },
        "Bb:9": {
            "A#:min": 8,
            "A:min": 4,
            "C": 3,
            "C#": 4,
            "C:min": 2,
            "D#": 4,
            "D:min": 5,
            "E:min": 1,
            "F": 16,
            "F:min": 18,
            "G#": 10,
            "G#:min": 5
        },
        "C:9": {
            "A#:min": 2,
            "A:min": 11,
            "C:min": 7,
            "D#": 1,
            "D:min": 1,
            "E": 1,
            "F": 7,
            "F:min": 5,
            "G": 2,
            "G#": 8,
            "G#:min": 3
        },
        "F:(3,5,b7,#9)": {
            "A#": 4,
            "A#:min": 6,
            "A:min": 1,
            "C#": 3,
            "C:min": 5,
            "D#": 14,
            "D#:min": 2,
            "D:min": 1,
            "F:min": 14,
            "G#": 15,
            "G#:min": 2
        },
        "F:7": {
            "A": 57,
            "A#": 4,
            "A#:min": 28,
            "A:min": 3,
            "C": 5,
            "C#": 31,
            "C#:min": 14,
            "C:min": 9,
            "D#": 11,
            "D#:min": 1,
            "D:min": 15,
            "F:min": 19,
            "G#": 11,
            "G#:min": 2
        },
        "N": {
            "A": 8,
            "A#": 3,
            "A#:min": 20,
            "C": 1,
            "C#": 3,
            "C#:min": 2,
            "C:min": 1,
            "D#": 3,
            "D#:min": 3,
            "D:min": 10,
            "F": 25,
            "F#:min": 11,
            "F:min": 4,
            "G#": 5,
            "G#:min": 2
        }
    },
    "west_coast_blues.flac": {
        "Ab": {
            "C#": 2,
            "E": 1,
            "F#": 2,
            "F:min": 2,
            "G#:min": 1,
            "G:min": 2
        },
        "Ab:7": {
            "A#": 4,
            "A#:min": 9,
            "C#": 3,
            "C:min": 1,
            "D": 2,
            "D#": 9,
            "D#:min": 23,
            "D:min": 4,
            "F": 4,
            "F#": 8,
            "F:min": 4,
            "G#:min": 1
        },
        "Ab:min7": {
            "C#": 1,
            "D:min": 2,
            "F#": 1,
            "F#:min": 1
        },
        "B:7": {
            "A#": 3,
            "A#:min": 8,
            "C#": 2,
            "D#": 2,
            "D#:min": 4,
            "D:min": 1,
            "F#": 1,
            "F#:min": 2,
            "F:min": 1,
            "G#": 1
        },
        "B:min7": {
            "A": 1,
            "A#": 5,
            "A#:min": 1,
            "B": 1,
            "D": 8,
            "D#:min": 1,
            "D:min": 4,
            "E": 3,
            "E:min": 1,
            "F#": 2,
            "F#:min": 4,
            "G": 2,
            "G:min": 1
        },
        "Bb": {
            "A#:min": 13,
            "C#": 1,
            "D": 2,
            "D:min": 1,
            "E": 1,
            "F#": 1,
            "F:min": 1,
            "G#:min": 1,
            "G:min": 6
        },
        "Bb:(3,5,6,7,#11)": {
            "C": 1
        },
        "Bb:(3,5,6,9,#11)": {
            "C": 1,
            "D#": 1
        },
        "Bb:7": {
            "A#:min": 17,
            "B": 1,
            "C#": 2,
            "D#": 15,
            "D#:min": 9,
            "D:min": 2,
            "E": 1,
            "F": 2,
            "F:min": 9,
            "G#": 3,
            "G:min": 11
        },
        "Bb:maj7": {
            "A#:min": 7,
            "D#": 1,
            "D:min": 8,
            "F": 4,
            "G:min": 1
        },
        "C:min7": {
            "A#": 7,
            "A#:min": 3,
            "C": 1,
            "D#": 8,
            "D:min": 6,
            "F": 3,
            "F#": 3,
            "G": 1,
            "G#": 2,
            "G:min": 8
        },
        "Cb:7": {
            "A": 1,
            "A:min": 1,
            "C": 1,
            "D:min": 1,
            "F#:min": 1
        },
        "D:min": {
            "A:min": 1,
            "D": 3,
            "E:min": 1,
            "F": 3,
            "G": 4,
            "G#:min": 2
        },
        "Db:7": {
            "A#": 3,
            "A#:min": 12,
            "B": 1,
            "D#": 1,
            "D:min": 1,
            "F#": 7,
            "G#:min": 1
        },
        "Db:min7": {
            "A": 2,
            "A#:min": 1,
            "B": 1,
            "B:min": 1,
            "D#": 1,
            "E": 3,
            "E:min": 1,
            "F#": 7,
            "F#:min": 1,
            "G": 3,
            "G#:min": 5
        },
        "E:7": {
            "A": 8,
            "A#:min": 1,
            "A:min": 2,
            "B": 2,
            "B:min": 9,
            "D": 6,
            "D#": 2,
            "D#:min": 1,
            "E:min": 1,
            "F#:min": 3,
            "G": 1,
            "G#:min": 3,
            "G:min": 1
        },
        "Eb": {
            "A#": 1,
            "A#:min": 1,
            "D#:min": 2,
            "G#": 1,
            "G#:min": 1,
            "G:min": 1
        },
        "Eb:7": {
            "A": 2,
            "A#": 3,
            "A#:min": 12,
            "A:min": 2,
            "C:min": 1,
            "D": 2,
            "D#:min": 13,
            "F#": 3,
            "G#": 4,
            "G#:min": 5,
            "G:min": 4
        },
        "Eb:min7": {
            "A#:min": 3,
            "D#": 5,
            "F#": 2,
            "G#:min": 1
        },
        "F:7": {
            "A#": 11,
            "A#:min": 10,
            "C:min": 11,
            "D#": 12,
            "D:min": 9,
            "G:min": 6
        },
        "G:7": {
            "A": 2,
            "A:min": 2,
            "C#:min": 1,
            "C:min": 1,
            "D#": 1,
            "D:min": 6,
            "E:min": 1,
            "F": 1,
            "G#:min": 1
        },
        "Gb:7": {
            "B": 1,
            "C#:min": 3,
            "C:min": 2,
            "D#": 2,
            "D#:min": 1,
            "E": 1,
            "F#:min": 2,
            "G#": 3,
            "G#:min": 2,
            "G:min": 1
        },
        "Gb:maj7": {
            "A#:min": 8,
            "B": 1,
            "C#": 2,
            "D#:min": 2,
            "F#:min": 1,
            "G#": 1
        },
        "Gb:min7": {
            "A": 1,
            "F#": 2
        },
        "N": {
            "A#": 4,
            "A#:min": 2,
            "C": 2,
            "C#": 4,
            "C#:min": 1,
            "C:min": 3,
            "D#": 2,
            "D:min": 4,
            "F:min": 1
        }
    },
    "wrap_your_troubles_in_dreams.flac": {
        "A": {
            "C": 1,
            "C#:min": 3
        },
        "A:maj6": {
            "A:min": 2,
            "B:min": 1,
            "C#": 2,
            "C#:min": 3,
            "D": 10,
            "D:min": 1,
            "F#:min": 19
        },
        "A:maj6/b7": {
            "C": 1,
            "D:min": 1
        },
        "B:7": {
            "A": 2,
            "A:min": 6,
            "C:min": 1,
            "D": 3,
            "D#:min": 2,
            "E": 3,
            "F": 1,
            "F#": 3,
            "F#:min": 8
        },
        "B:min7": {
            "A:min": 1,
            "B": 1,
            "D": 3,
            "E": 1,
            "E:min": 1,
            "F#:min": 8
        },
        "Bb:hdim7": {
            "A": 2,
            "C#:min": 1
        },
        "C#:7": {
            "A:min": 1,
            "B": 2,
            "B:min": 1,
            "C": 1,
            "C#:min": 2,
            "D": 1,
            "D#:min": 1,
            "D:min": 1,
            "E": 2,
            "E:min": 1,
            "F#": 4,
            "F#:min": 2,
            "G#:min": 2
        },
        "C#:min7": {
            "A": 6,
            "B:min": 1,
            "C#": 3,
            "D": 2,
            "F#": 1,
            "F#:min": 9
        },
        "C:dim7": {
            "A:min": 1,
            "B": 2,
            "B:min": 2,
            "D": 2,
            "F#:min": 4
        },
        "D#:7": {
            "A": 2,
            "C#": 1,
            "C#:min": 2,
            "F#:min": 4,
            "G#": 4
        },
        "D:7": {
            "B:min": 3,
            "C#": 1,
            "F#": 2,
            "F#:min": 3
        },
        "E:7": {
            "A": 10,
            "A:min": 4,
            "B:min": 2,
            "C#:min": 5,
            "D": 4,
            "F#:min": 10
        },
        "F#:7": {
            "A:min": 1,
            "B": 1,
            "D#:min": 1,
            "E": 1,
            "E:min": 2,
            "F": 1,
            "F#:min": 3,
            "G": 1
        },
        "F#:min7": {
            "A": 3,
            "A:min": 8,
            "B": 5,
            "B:min": 3,
            "C#": 2,
            "C#:min": 7,
            "C:min": 3,
            "D": 15,
            "D:min": 2,
            "E": 1,
            "F": 2
        },
        "G#:7": {
            "B": 2,
            "B:min": 2,
            "C#": 3,
            "C#:min": 7,
            "E": 2,
            "F#:min": 5,
            "G#:min": 5
        },
        "G:dim7": {
            "F#:min": 1
        },
        "N": {
            "A": 3,
            "B:min": 2,
            "D": 7,
            "D:min": 1,
            "F#": 1,
            "F#:min": 9,
            "G#": 1,
            "G:min": 2
        }
    }
}